geniusrise_openai/__init__.py
geniusrise_openai/base.py
geniusrise_openai/classification.py
geniusrise_openai/commonsense_reasoning.py
geniusrise_openai/instruction_tuning.py
geniusrise_openai/language_model.py
geniusrise_openai/ner.py
geniusrise_openai/question_answering.py
geniusrise_openai/sentiment_analysis.py
geniusrise_openai/summarization.py
geniusrise_openai/translation.py
geniusrise_openai-0.1.3.dist-info/METADATA
geniusrise_openai-0.1.3.dist-info/WHEEL
geniusrise_openai-0.1.3.dist-info/top_level.txt
geniusrise_openai-0.1.3.dist-info/RECORD
